eyadgpt-6.8.6.dist-info/licenses/LICENSE
revChatGPT/V1.py
revChatGPT/V3.py
revChatGPT/__init__.py
revChatGPT/__main__.py
revChatGPT/typings.py
revChatGPT/utils.py
revChatGPT/version.py
revChatGPT/config/enable_internet.json
eyadgpt-6.8.6.dist-info/METADATA
eyadgpt-6.8.6.dist-info/WHEEL
eyadgpt-6.8.6.dist-info/top_level.txt
eyadgpt-6.8.6.dist-info/RECORD
