Metadata-Version: 2.4
Name: EyadGPT
Version: 6.8.6
Summary: ChatGPT is a reverse engineering of OpenAI's ChatGPT API
Home-page: https://github.com/acheong08/ChatGPT
Author: Antonio Cheong
Author-email: acheong@student.dalat.org
License: GNU General Public License v2.0
Project-URL: Bug Report, https://github.com/acheong08/ChatGPT/issues/new?assignees=&labels=bug-report&template=bug_report.yml&title=%5BBug%5D%3A+
Project-URL: Feature request, https://github.com/acheong08/ChatGPT/issues/new?assignees=&labels=enhancement&template=feature_request.yml&title=%5BFeature+Request%5D%3A+
Classifier: License :: OSI Approved :: GNU General Public License v2 (GPLv2)
Classifier: Intended Audience :: Developers
Classifier: Intended Audience :: End Users/Desktop
Classifier: Natural Language :: English
Classifier: Topic :: Software Development :: Libraries :: Python Modules
Classifier: Programming Language :: Python :: 3 :: Only
Classifier: Programming Language :: Python :: 3.9
Classifier: Programming Language :: Python :: 3.10
Classifier: Programming Language :: Python :: 3.11
License-File: LICENSE
Requires-Dist: OpenAIAuth>=3.0.0
Requires-Dist: requests[socks]
Requires-Dist: httpx[socks]
Requires-Dist: prompt-toolkit
Requires-Dist: tiktoken>=0.3.0
Requires-Dist: openai
Requires-Dist: rich
Dynamic: author
Dynamic: author-email
Dynamic: classifier
Dynamic: description
Dynamic: description-content-type
Dynamic: home-page
Dynamic: license
Dynamic: license-file
Dynamic: project-url
Dynamic: requires-dist
Dynamic: summary
